Workbook

Sheet Assumptions
A1: Limber — Global Market Sizing & Revenue Model
A2: Neuroplasticity-core consumer app · Worldwide · TAM/SAM/SOM + 3-Year Revenue + Business Model Canvas · June 2026
A3: Blue=input · Black=formula · Green=cross-sheet link · Yellow=key assumption. Sources on Sources tab.
A5: MARKET INPUTS (global) | B5: Value | F5: Source
A6: Cognitively-concerned, digitally-active adults (M) [TAM users] | B6: 730 | F6: Derived from regional adult/ smartphone + concern data
A7: Income/motivation-qualified adults (M) [SAM users] | B7: 110 | F7: Income-filtered, motivation-matched subset
A8: Blended B2C ARPU ($/paying user/yr) | B8: 80 | F8: Calm/Headspace/BrainHQ benchmark blend
A9: Mental-health apps market 2025 ($B) | B9: 9.94 | F9: MarketsandMarkets 2025
A10: Neurotechnology market 2025 ($B) | B10: 16 | F10: Precedence / Fortune BI 2025
A11: Brain-fitness software market 2025 ($B) | B11: 6 | F11: Global Growth Insights / FMI 2025
A13: MONETIZATION INPUTS | B13: Value | F13: Basis
A14: Plus price ($/yr) | B14: 89 | F14: $12.99/mo anchor vs Calm/Headspace
A15: Pro price ($/yr) | B15: 199 | F15: $19.99/mo incl. coaching
A16: Blended paid ARPU ($/yr) | B16: 95 | F16: Mix of Plus/Pro + annual skew
A17: Free-to-paid conversion | B17: 0.04 | F17: Beachhead = science-literate, higher-intent
A18: B2B employer PEPM ($/employee/month) | B18: 6 | F18: Corporate cognitive-wellbeing benchmark
A19: Hardware/biofeedback net ARPU ($/yr) | B19: 120 | F19: Optional EEG/HRV attach
A20: DiGA/clinical reimbursed ($/90-day course) | B20: 250 | F20: Germany DiGA mean ~€227

Sheet TAM_SAM_SOM
A1: TAM · SAM · SOM — Global
A2: Bottom-up (users × annual value), cross-checked vs cited market reports. Plan to SAM/SOM, not headline TAM.
A4: BOTTOM-UP | B4: Users (M) | C4: Value/user ($/yr) | D4: Market ($B) | F4: Logic
A5: TAM — cognitively-concerned digital adults | B5: =Assumptions!B6 -> 730 | C5: =Assumptions!B8 -> 80 | D5: =B5*C5/1000 -> 58.4 | F5: 730M adults × $80/yr if monetized
A6: SAM — income/motivation-qualified | B6: =Assumptions!B7 -> 110 | C6: =Assumptions!B8 -> 80 | D6: =B6*C6/1000 -> 8.8 | F6: 110M reachable, willing-to-pay × $80/yr
A7: SOM — obtainable by Year 3 | B7: =B6*0.012 -> 1.32 | C7: =Assumptions!B8 -> 80 | D7: ='Revenue Model'!E20/1000000000 -> 0.10342 | F7: ~1.2% of SAM; value = Year-3 modelled revenue (~$0.1B)
A9: TOP-DOWN CROSS-CHECK ($B, 2025)
A10: Mental-health apps market | B10: =Assumptions!B9 -> 9.94 | F10: MarketsandMarkets (SAM aligns with this)
A11: Neurotechnology market | B11: =Assumptions!B10 -> 16
A12: Brain-fitness software market | B12: =Assumptions!B11 -> 6
A14: READ: SAM (~$8.8B) aligns with the cited mental-health-app market; SOM is the bottom-up Year-3 build, not a top-down slice.

Sheet Revenue Model
A1: 3-Year Revenue Build — Global
A2: Beachhead = NA optimizers/longevity (high WTP), expanding to aging, students, clinical. B2B employer = scale engine.
A4: Driver | B4: Unit | C4: Year 1 | D4: Year 2 | E4: Year 3 | F4: Note
A6: B2C — CONSUMER SUBSCRIPTIONS
A7: Paying B2C users | B7: count | C7: 40000 | D7: 200000 | E7: 700000 | F7: Freemium @ ~4% conv; creator/longevity-led
A8: B2C revenue ($) | C8: =C7*Assumptions!$B$16 -> 3800000 | D8: =D7*Assumptions!$B$16 -> 19000000 | E8: =E7*Assumptions!$B$16 -> 66500000 | F8: users × $95 blended ARPU
A9: B2B — EMPLOYER (cognitive wellbeing)
A10: Employer clients | B10: count | C10: 5 | D10: 30 | E10: 90 | F10: Corporate wellbeing/longevity benefit
A11: Avg seats/client | B11: seats | C11: 2000 | D11: 3000 | E11: 4000 | F11: Mid-large enterprises
A12: Total seats | C12: =C10*C11 -> 10000 | D12: =D10*D11 -> 90000 | E12: =E10*E11 -> 360000
A13: B2B revenue ($) | C13: =C12*Assumptions!$B$18*12 -> 720000 | D13: =D12*Assumptions!$B$18*12 -> 6480000 | E13: =E12*Assumptions!$B$18*12 -> 25920000 | F13: seats × $6 PEPM × 12
A14: HARDWARE / BIOFEEDBACK ATTACH
A15: Attach users | B15: count | C15: 3000 | D15: 20000 | E15: 50000 | F15: Optional EEG/HRV integrations
A16: Hardware revenue ($) | C16: =C15*Assumptions!$B$19 -> 360000 | D16: =D15*Assumptions!$B$19 -> 2400000 | E16: =E15*Assumptions!$B$19 -> 6000000
A17: DiGA / CLINICAL (Europe)
A18: Reimbursed 90-day courses | B18: count | C18: 0 | D18: 5000 | E18: 20000 | F18: Germany DiGA listing (credibility+payer)
A19: DiGA revenue ($) | C19: =C18*Assumptions!$B$20 -> 0 | D19: =D18*Assumptions!$B$20 -> 1250000 | E19: =E18*Assumptions!$B$20 -> 5000000
A20: TOTAL REVENUE ($) | C20: =C8+C13+C16+C19 -> 4880000 | D20: =D8+D13+D16+D19 -> 29130000 | E20: =E8+E13+E16+E19 -> 103420000
A21: TOTAL REVENUE ($M) | C21: =C20/1000000 -> 4.88 | D21: =D20/1000000 -> 29.13 | E21: =E20/1000000 -> 103.42
A23: Memo: % revenue from B2B | C23: =C13/C20 -> 0.14754098 | D23: =D13/D20 -> 0.22245108 | E23: =E13/E20 -> 0.25062851

Sheet Business Model Canvas
A1: Business Model Canvas — Limber
A2: Neuroplasticity-core, global, evidence-honest. Osterwalder 9-block canvas.
A4: ① Key Partners | B4: ② Key Activities | C4: ③ Value Propositions | D4: ④ Customer Relationships | E4: ⑤ Customer Segments
A5: • Academic neuroscience labs (efficacy studies) • Clinical advisory board • Wearable/biometric platforms (Oura, Apple Health, EEG) • Employers / benefits brokers (B2B) • German DiGA / payers (EU) • Creators & longevity communities | B5: • Build the Prime→Train→Consolidate loop • Adaptive-difficulty training engine (~85% zone) • Honest baseline assessments & analytics • Run & publish efficacy studies • World-class, accessible, localized UX | C5: • Train a more adaptable mind — the way science says it changes • The integrated, HONEST plasticity stack (practice + lifestyle levers) • Progress vs your own baseline (no overclaims) • Personalized to your variability • Optional biofeedback | D5: • Self-serve + adaptive personalization • AI/human coaching (retention lever) • Transparent evidence library • Community & cohorts (opt-in) • B2B admin dashboards (aggregate) | E5: • Optimizers/biohackers (beachhead) • Worried-well aging • Students/learners • Clinical/recovery (ADHD, stroke, long-COVID) • Longevity enthusiasts • Buyer: employers / clinicians
A12: ⑥ Key Resources | C12: ⑦ Channels
A13: • Proprietary adaptive training + personalization engine • Published efficacy evidence • Clinical advisory board & brand trust • Localized content & design system • Behavioral-science + neuro talent | C13: • App stores + creator/longevity marketing • Employer benefits / brokers • Clinics & DiGA (EU) • Wearable ecosystem partnerships • Evidence-led PR & community
A20: ⑧ Cost Structure | C20: 💰 Revenue Streams
A21: • R&D: training engine, personalization, content • Efficacy studies & clinical/regulatory (DiGA) • Coaching network (variable) • Cloud/infra + biometric integrations • Localization, accessibility, design • Trust & evidence marketing | C21: • B2C: Free / Plus $12.99/mo·$89/yr / Pro $19.99/mo • B2B employer: ~$4–8 PEPM (scale engine) • Hardware/biofeedback attach • DiGA/clinical reimbursement (EU) Year-3 modelled revenue: see Revenue Model (~$100M)

Sheet Sources
A1: Sources & Method
A3: Method | B3: Bottom-up (users × ARPU) primary; cited market reports as cross-check. All inputs editable on Assumptions tab.
A4: Market size | B4: MarketsandMarkets (mental-health apps $9.94B→22.73B); Precedence/Fortune BI (neurotech); Global Growth Insights/FMI (brain fitness).
A5: Users | B5: Regional adult + smartphone + cognitive-concern data (Alzheimer’s ADI; biohacking surveys; DataReportal).
A6: Pricing | B6: Calm/Headspace/BrainHQ public pricing; Calm Business PEPM; DiGA mean €227/90-day (BfArM/npj Digital Medicine).
A7: Conversion | B7: Global freemium ~2–5%; beachhead (science-literate, high-intent) ~4% assumed.
A8: Caveat | B8: SOM is a planning target, not a forecast. Adherence (~70% churn in 100 days) and far-transfer overclaiming (FTC) are the top risks.

Sheet Unit Economics
A1: Unit Economics & Sensitivity
A2: Added per panel review. Blue=input. Shows why D2C must be organic/creator-led, not paid.
A4: B2C UNIT ECONOMICS
A5: Blended paid ARPU ($/yr) | B5: 95 | F5: From Assumptions
A6: Gross margin (%) | B6: 0.75 | F6: Software-heavy; coaching variable
A7: Avg paid lifetime (years) | B7: 2 | F7: ~50% annual retention assumption
A8: Blended CAC ($/paying user) - organic/creator-led | B8: 25 | F8: Low because trust/creator-led, not paid UA
A9: LTV ($) | B9: =B5*B6*B7 -> 142.5 | F9: ARPU x GM x lifetime
A10: LTV : CAC | B10: =B9/B8 -> 5.7 | F10: Target >= 3.0x
A11: CAC payback (months) | B11: =B8/(B5*B6/12) -> 4.2105263 | F11: Target <= 12
A13: WHY PAID D2C DOES NOT WORK (Year-3 = 700k paying users)
A14: Year-3 paying B2C users | B14: 700000 | F14: From Revenue Model
A15: Registered users needed @ conversion | B15: 2% | C15: 4% (base) | D15: 6%
A16: Registered users needed | B16: =$B$14/0.02 -> 35000000 | C16: =$B$14/0.04 -> 17500000 | D16: =$B$14/0.06 -> 11666667
A17: Hypothetical paid CAC per registrant ($) | B17: 15 | F17: Even a low $15 paid CPI
A18: Paid acquisition cost to hit Year-3 | B18: =B16*$B$17 -> 525000000 | C18: =C16*$B$17 -> 262500000 | D18: =D16*$B$17 -> 175000000 | F18: At 4% conv, ~$262M paid spend > total revenue. Conclusion: D2C must be organic/creator-led; paid budget goes to B2B.
A20: B2B UNIT ECONOMICS
A21: Avg seats per client | B21: 4000
A22: PEPM ($/employee/month) | B22: 6
A23: B2B CAC per deal ($) - enterprise sales | B23: 40000 | F23: Sales + CS; was missing from BMC
A24: B2B gross margin (%) | B24: 0.8
A25: Annual contract value ($) | B25: =B21*B22*12 -> 288000 | F25: seats x PEPM x 12
A26: B2B CAC payback (months) | B26: =B23/(B25*B24/12) -> 2.0833333 | F26: Target <= 18
A28: DiGA / clinical track is a CREDIBILITY + reimbursement play, not near-term revenue — treat as cost center in v1; modest revenue only after EU listing (v2).
